LICENSE
NOTICE
README.md
setup.cfg
setup.py
alpaca_trade_api/__init__.py
alpaca_trade_api/__main__.py
alpaca_trade_api/common.py
alpaca_trade_api/entity.py
alpaca_trade_api/entity_v2.py
alpaca_trade_api/rest.py
alpaca_trade_api/rest_async.py
alpaca_trade_api/stream.py
raze_alpaca_api.egg-info/PKG-INFO
raze_alpaca_api.egg-info/SOURCES.txt
raze_alpaca_api.egg-info/dependency_links.txt
raze_alpaca_api.egg-info/requires.txt
raze_alpaca_api.egg-info/top_level.txt
tests/test_rest.py